Metadata-Version: 2.1
Name: myst-parser
Version: 0.19.2
Summary: An extended [CommonMark](https://spec.commonmark.org/) compliant parser,
Keywords: markdown,lexer,parser,development,docutils,sphinx
Author-email: Chris Sewell <chrisj_sewell@hotmail.com>
Requires-Python: >=3.7
Classifier: Development Status :: 4 - Beta
Classifier: Framework :: Sphinx :: Extension
Classifier: Intended Audience :: Developers
Classifier: License :: OSI Approved :: MIT License
Classifier: Programming Language :: Python :: 3
Classifier: Programming Language :: Python :: 3 :: Only
Classifier: Programming Language :: Python :: 3.7
Classifier: Programming Language :: Python :: 3.8
Classifier: Programming Language :: Python :: 3.9
Classifier: Programming Language :: Python :: 3.10
Classifier: Programming Language :: Python :: Implementation :: CPython
Classifier: Programming Language :: Python :: Implementation :: PyPy
Classifier: Topic :: Software Development :: Libraries :: Python Modules
Classifier: Topic :: Text Processing :: Markup
Requires-Dist: docutils>=0.15,<0.20
Requires-Dist: jinja2
Requires-Dist: markdown-it-py>=1.0.0,<3.0.0
Requires-Dist: mdit-py-plugins~=0.3.4
Requires-Dist: pyyaml
Requires-Dist: sphinx>=5,<7
Requires-Dist: typing-extensions; python_version < "3.8"
Requires-Dist: pre-commit~=3.0 ; extra == "code_style"
Requires-Dist: linkify-it-py~=1.0 ; extra == "linkify"
Requires-Dist: ipython ; extra == "rtd"
Requires-Dist: sphinx-book-theme==1.0.0rc2 ; extra == "rtd"
Requires-Dist: pydata-sphinx-theme==v0.13.0rc4 ; extra == "rtd"
Requires-Dist: sphinx-design2 ; extra == "rtd"
Requires-Dist: sphinx-copybutton ; extra == "rtd"
Requires-Dist: sphinxext-rediraffe~=0.2.7 ; extra == "rtd"
Requires-Dist: sphinxext-opengraph~=0.7.5 ; extra == "rtd"
Requires-Dist: sphinx-pyscript ; extra == "rtd"
Requires-Dist: sphinx-tippy>=0.3.1 ; extra == "rtd"
Requires-Dist: sphinx-autodoc2~=0.4.2 ; extra == "rtd"
Requires-Dist: sphinx-togglebutton ; extra == "rtd"
Requires-Dist: beautifulsoup4 ; extra == "testing"
Requires-Dist: coverage[toml] ; extra == "testing"
Requires-Dist: pytest>=7,<8 ; extra == "testing"
Requires-Dist: pytest-cov ; extra == "testing"
Requires-Dist: pytest-regressions ; extra == "testing"
Requires-Dist: pytest-param-files~=0.3.4 ; extra == "testing"
Requires-Dist: sphinx-pytest ; extra == "testing"
Requires-Dist: pygments ; extra == "testing-docutils"
Requires-Dist: pytest>=7,<8 ; extra == "testing-docutils"
Requires-Dist: pytest-param-files~=0.3.4 ; extra == "testing-docutils"
Project-URL: Documentation, https://myst-parser.readthedocs.io
Project-URL: Homepage, https://github.com/executablebooks/MyST-Parser
Provides-Extra: code_style
Provides-Extra: linkify
Provides-Extra: rtd
Provides-Extra: testing
Provides-Extra: testing-docutils
